intrepydd/__init__.py
intrepydd/arrayopt.py
intrepydd/astutils.py
intrepydd/codegen.py
intrepydd/defuse.py
intrepydd/escapeanalysis.py
intrepydd/escapetransform.py
intrepydd/glb.py
intrepydd/lang.py
intrepydd/launcher.py
intrepydd/libfuncs.py
intrepydd/licmarray.py
intrepydd/licmast.py
intrepydd/mytypes.py
intrepydd/opexpansion.py
intrepydd/pyddc.py
intrepydd/ret_to_assign.py
intrepydd/runcppimport.py
intrepydd/scalarpriv.py
intrepydd/scanner.py
intrepydd/symboltable.py
intrepydd/transform1.py
intrepydd/transform2.py
intrepydd/typeinfer.py
intrepydd/utils.py
tests/__init__.py
tests/bench_array_add_mul.py
tests/check_mem.py
tests/check_mem1.py
tests/kernel_0cd8f6dca2198f6926b0fe80a2ab1df5bf6cfe9106ad8df61177ae189c01e086.py
tests/kernel_1f1740e57416f975529ebaa93d55c21cf821f328ce36195ddc0b8d81d73c17c9.py
tests/test_alloc_hoist.py
tests/test_arithmetic.py
tests/test_array_add_mul.py
tests/test_fib.py
tests/test_licm.py
tests/test_matmul.py
tests/test_sinkhorn_src.py
tests/test_slice.py
intrepydd-0.1.15.dist-info/METADATA
intrepydd-0.1.15.dist-info/WHEEL
intrepydd-0.1.15.dist-info/top_level.txt
intrepydd-0.1.15.dist-info/RECORD
